jeelink/__init__.py
jeelink/gateway.py
jeelink/helper.py
jeelink/device/__init__.py
jeelink/device/lacrosse.py
jeelink/device/pca301.py
jeelink/sketch/__init__.py
jeelink/sketch/lacrosse.py
jeelink/sketch/pca301.py
jeelink-0.2.2.dist-info/METADATA
jeelink-0.2.2.dist-info/WHEEL
jeelink-0.2.2.dist-info/top_level.txt
jeelink-0.2.2.dist-info/RECORD
