Metadata-Version: 2.1
Name: jeelink
Version: 0.2.2
Summary: Python interface for jeelink sketches
Author: Andre Basche
License: MIT
Project-URL: GitHub, https://github.com/Andre0512/jeelink
Project-URL: PyPI, https://pypi.org/project/jeelink/
Keywords: smart home automation
Platform: any
Classifier: Development Status :: 2 - Pre-Alpha
Classifier: Environment :: Console
Classifier: License :: OSI Approved :: MIT License
Classifier: Natural Language :: English
Classifier: Operating System :: OS Independent
Classifier: Programming Language :: Python :: 3.8
Classifier: Programming Language :: Python :: 3.9
Classifier: Programming Language :: Python :: 3.10
Classifier: Programming Language :: Python :: 3.11
Classifier: Topic :: Software Development :: Libraries :: Python Modules
Requires-Python: >=3.8
Requires-Dist: pyserial
Requires-Dist: pyserial-asyncio
